vctube/__init__.py
vctube/caption.py
vctube/utils.py
vctube/vctube.py
vctube-1.3.dist-info/LICENSE
vctube-1.3.dist-info/METADATA
vctube-1.3.dist-info/WHEEL
vctube-1.3.dist-info/top_level.txt
vctube-1.3.dist-info/RECORD
