Metadata-Version: 2.1
Name: vctube
Version: 1.3
Summary: A package for crawling and processing audio, caption from Youtube
Home-page: https://github.com/zldzmfoq12/aud-crawler
Author: Seugnhun Jeong
Author-email: zldzmfoq12@naver.com
License: UNKNOWN
Keywords: aud_crawler
Platform: UNKNOWN
Classifier: Programming Language :: Python :: 3
Classifier: License :: OSI Approved :: MIT License
Classifier: Operating System :: OS Independent
Requires-Python: ==3.6
Requires-Dist: pandas
Requires-Dist: pydub
Requires-Dist: tqdm
Requires-Dist: youtube-dl
Requires-Dist: youtube-transcript-api
